{
"meta":{"test_sets":[],"test_metrics":[],"learn_metrics":[{"best_value":"Min","name":"RMSE"}],"launch_mode":"Train","parameters":"","iteration_count":100,"learn_sets":["learn"],"name":"experiment"},
"iterations":[
{"learn":[14.005006],"iteration":0,"passed_time":0.001100006803,"remaining_time":0.1089006735},
{"learn":[13.14441192],"iteration":1,"passed_time":0.002611070979,"remaining_time":0.127942478},
{"learn":[12.34258257],"iteration":2,"passed_time":0.004009348614,"remaining_time":0.1296356052},
{"learn":[11.64527793],"iteration":3,"passed_time":0.005479919061,"remaining_time":0.1315180575},
{"learn":[11.02766183],"iteration":4,"passed_time":0.006633763351,"remaining_time":0.1260415037},
{"learn":[10.43485794],"iteration":5,"passed_time":0.007503938711,"remaining_time":0.1175617065},
{"learn":[9.890641275],"iteration":6,"passed_time":0.009203755052,"remaining_time":0.12227846},
{"learn":[9.492161212],"iteration":7,"passed_time":0.01105181296,"remaining_time":0.127095849},
{"learn":[9.105082953],"iteration":8,"passed_time":0.0121133488,"remaining_time":0.1224794156},
{"learn":[8.674157135],"iteration":9,"passed_time":0.01316654853,"remaining_time":0.1184989368},
{"learn":[8.341743544],"iteration":10,"passed_time":0.01494834665,"remaining_time":0.1209457138},
{"learn":[8.049372916],"iteration":11,"passed_time":0.01668207764,"remaining_time":0.1223352361},
{"learn":[7.757318612],"iteration":12,"passed_time":0.01762361822,"remaining_time":0.1179426758},
{"learn":[7.522206899],"iteration":13,"passed_time":0.01874513195,"remaining_time":0.1151486677},
{"learn":[7.297756655],"iteration":14,"passed_time":0.02127769379,"remaining_time":0.1205735981},
{"learn":[7.088359431],"iteration":15,"passed_time":0.02265051137,"remaining_time":0.1189151847},
{"learn":[6.882113791],"iteration":16,"passed_time":0.02378329816,"remaining_time":0.1161184557},
{"learn":[6.704728832],"iteration":17,"passed_time":0.02485589922,"remaining_time":0.1132324298},
{"learn":[6.563881962],"iteration":18,"passed_time":0.02616028662,"remaining_time":0.1115254324},
{"learn":[6.418790279],"iteration":19,"passed_time":0.02828900864,"remaining_time":0.1131560345},
{"learn":[6.315756953],"iteration":20,"passed_time":0.03003998743,"remaining_time":0.1130075717},
{"learn":[6.210157751],"iteration":21,"passed_time":0.03116082703,"remaining_time":0.1104792958},
{"learn":[6.115058449],"iteration":22,"passed_time":0.03230749672,"remaining_time":0.1081598803},
{"learn":[6.014819884],"iteration":23,"passed_time":0.03392048622,"remaining_time":0.107414873},
{"learn":[5.93117229],"iteration":24,"passed_time":0.03529158014,"remaining_time":0.1058747404},
{"learn":[5.844857622],"iteration":25,"passed_time":0.03719178906,"remaining_time":0.1058535535},
{"learn":[5.771145213],"iteration":26,"passed_time":0.03813956704,"remaining_time":0.1031180887},
{"learn":[5.704018229],"iteration":27,"passed_time":0.03919217011,"remaining_time":0.100779866},
{"learn":[5.665806474],"iteration":28,"passed_time":0.04096573949,"remaining_time":0.1002954312},
{"learn":[5.616500369],"iteration":29,"passed_time":0.04263678879,"remaining_time":0.09948584052},
{"learn":[5.558023666],"iteration":30,"passed_time":0.04379035814,"remaining_time":0.09746886167},
{"learn":[5.510080976],"iteration":31,"passed_time":0.04494031565,"remaining_time":0.09549817075},
{"learn":[5.468747792],"iteration":32,"passed_time":0.04622847488,"remaining_time":0.09385781263},
{"learn":[5.429275534],"iteration":33,"passed_time":0.04822595656,"remaining_time":0.09361509215},
{"learn":[5.402117324],"iteration":34,"passed_time":0.04955444272,"remaining_time":0.09202967933},
{"learn":[5.367635151],"iteration":35,"passed_time":0.05063916045,"remaining_time":0.09002517414},
{"learn":[5.345181232],"iteration":36,"passed_time":0.05172178218,"remaining_time":0.0880668183},
{"learn":[5.319151269],"iteration":37,"passed_time":0.06664058528,"remaining_time":0.108729376},
{"learn":[5.296134146],"iteration":38,"passed_time":0.06829214544,"remaining_time":0.1068159198},
{"learn":[5.269629003],"iteration":39,"passed_time":0.06939876891,"remaining_time":0.1040981534},
{"learn":[5.251147059],"iteration":40,"passed_time":0.07031819285,"remaining_time":0.1011895946},
{"learn":[5.248003302],"iteration":41,"passed_time":0.07096239632,"remaining_time":0.09799569016},
{"learn":[5.232376509],"iteration":42,"passed_time":0.07326838118,"remaining_time":0.09712320295},
{"learn":[5.213524255],"iteration":43,"passed_time":0.07469608617,"remaining_time":0.09506774604},
{"learn":[5.189691584],"iteration":44,"passed_time":0.07577679365,"remaining_time":0.09261608113},
{"learn":[5.166052198],"iteration":45,"passed_time":0.0769353764,"remaining_time":0.09031544186},
{"learn":[5.140406659],"iteration":46,"passed_time":0.07903367788,"remaining_time":0.08912308357},
{"learn":[5.118929684],"iteration":47,"passed_time":0.0802713787,"remaining_time":0.08696066026},
{"learn":[5.108792602],"iteration":48,"passed_time":0.08121502027,"remaining_time":0.08452991906},
{"learn":[5.098141225],"iteration":49,"passed_time":0.08253508481,"remaining_time":0.08253508481},
{"learn":[5.085926393],"iteration":50,"passed_time":0.08395709652,"remaining_time":0.08066466136},
{"learn":[5.067816804],"iteration":51,"passed_time":0.08541955557,"remaining_time":0.07884882052},
{"learn":[5.049834901],"iteration":52,"passed_time":0.0867668065,"remaining_time":0.07694414916},
{"learn":[5.03838627],"iteration":53,"passed_time":0.08785762629,"remaining_time":0.07484168165},
{"learn":[5.033534248],"iteration":54,"passed_time":0.08854560977,"remaining_time":0.072446408},
{"learn":[5.023726885],"iteration":55,"passed_time":0.08974449835,"remaining_time":0.07051353442},
{"learn":[5.01290392],"iteration":56,"passed_time":0.09117778734,"remaining_time":0.06878324308},
{"learn":[5.005569127],"iteration":57,"passed_time":0.09292578202,"remaining_time":0.06729108353},
{"learn":[4.989969032],"iteration":58,"passed_time":0.09413733754,"remaining_time":0.06541747185},
{"learn":[4.976762446],"iteration":59,"passed_time":0.09517787915,"remaining_time":0.06345191943},
{"learn":[4.967222715],"iteration":60,"passed_time":0.09661763947,"remaining_time":0.06177193343},
{"learn":[4.954407599],"iteration":61,"passed_time":0.09795804712,"remaining_time":0.06003880307},
{"learn":[4.942125056],"iteration":62,"passed_time":0.0993280474,"remaining_time":0.0583355199},
{"learn":[4.930230716],"iteration":63,"passed_time":0.100379895,"remaining_time":0.05646369096},
{"learn":[4.921695642],"iteration":64,"passed_time":0.1013496397,"remaining_time":0.05457288293},
{"learn":[4.906405625],"iteration":65,"passed_time":0.102527842,"remaining_time":0.05281737315},
{"learn":[4.894330248],"iteration":66,"passed_time":0.1042559997,"remaining_time":0.05134997001},
{"learn":[4.88211557],"iteration":67,"passed_time":0.1059995922,"remaining_time":0.04988216105},
{"learn":[4.877946398],"iteration":68,"passed_time":0.1071287515,"remaining_time":0.04813030863},
{"learn":[4.863182126],"iteration":69,"passed_time":0.1080657771,"remaining_time":0.04631390449},
{"learn":[4.84646533],"iteration":70,"passed_time":0.1099791078,"remaining_time":0.04492104403},
{"learn":[4.838014752],"iteration":71,"passed_time":0.1117151307,"remaining_time":0.04344477307},
{"learn":[4.82981137],"iteration":72,"passed_time":0.1128876374,"remaining_time":0.04175296179},
{"learn":[4.817094767],"iteration":73,"passed_time":0.1137685835,"remaining_time":0.03997274556},
{"learn":[4.808314151],"iteration":74,"passed_time":0.1155436971,"remaining_time":0.0385145657},
{"learn":[4.796235023],"iteration":75,"passed_time":0.1172255727,"remaining_time":0.03701860191},
{"learn":[4.784434534],"iteration":76,"passed_time":0.1187137867,"remaining_time":0.03545996226},
{"learn":[4.774402487],"iteration":77,"passed_time":0.1197345715,"remaining_time":0.0337712894},
{"learn":[4.76731896],"iteration":78,"passed_time":0.1227576965,"remaining_time":0.03263179273},
{"learn":[4.75934113],"iteration":79,"passed_time":0.1242042928,"remaining_time":0.0310510732},
{"learn":[4.754106378],"iteration":80,"passed_time":0.1253286568,"remaining_time":0.02939807999},
{"learn":[4.744002932],"iteration":81,"passed_time":0.1266127241,"remaining_time":0.027793037},
{"learn":[4.731700554],"iteration":82,"passed_time":0.128208618,"remaining_time":0.02625959647},
{"learn":[4.723284153],"iteration":83,"passed_time":0.1298294371,"remaining_time":0.02472941659},
{"learn":[4.712232782],"iteration":84,"passed_time":0.1309331175,"remaining_time":0.02310584426},
{"learn":[4.703046867],"iteration":85,"passed_time":0.1320489767,"remaining_time":0.02149634504},
{"learn":[4.698601855],"iteration":86,"passed_time":0.1331205527,"remaining_time":0.01989157684},
{"learn":[4.692429407],"iteration":87,"passed_time":0.1345061906,"remaining_time":0.01834175327},
{"learn":[4.675027364],"iteration":88,"passed_time":0.1364627188,"remaining_time":0.01686617873},
{"learn":[4.662368584],"iteration":89,"passed_time":0.1381339553,"remaining_time":0.01534821725},
{"learn":[4.646206172],"iteration":90,"passed_time":0.1395360311,"remaining_time":0.01380026681},
{"learn":[4.641245848],"iteration":91,"passed_time":0.1414961362,"remaining_time":0.01230401185},
{"learn":[4.633900435],"iteration":92,"passed_time":0.1432507775,"remaining_time":0.01078231658},
{"learn":[4.624738236],"iteration":93,"passed_time":0.1447756851,"remaining_time":0.009241001174},
{"learn":[4.612798287],"iteration":94,"passed_time":0.1460669868,"remaining_time":0.007687736146},
{"learn":[4.605222001],"iteration":95,"passed_time":0.147848179,"remaining_time":0.006160340792},
{"learn":[4.601725912],"iteration":96,"passed_time":0.1496735301,"remaining_time":0.004629078252},
{"learn":[4.59722371],"iteration":97,"passed_time":0.1507456093,"remaining_time":0.003076441006},
{"learn":[4.580235665],"iteration":98,"passed_time":0.1517010105,"remaining_time":0.00153233344},
{"learn":[4.57591791],"iteration":99,"passed_time":0.154270044,"remaining_time":0}
]}